octopus/__init__.py
octopus/main.py
octopus/controllers/__init__.py
octopus/controllers/base.py
octopus/core/__init__.py
octopus/core/exc.py
octopus/core/version.py
octopus/ext/__init__.py
octopus/plugins/__init__.py
octopus/templates/__init__.py
octopus/templates/command1.jinja2
octopus_cli-0.0.1.dist-info/LICENSE.md
octopus_cli-0.0.1.dist-info/METADATA
octopus_cli-0.0.1.dist-info/WHEEL
octopus_cli-0.0.1.dist-info/entry_points.txt
octopus_cli-0.0.1.dist-info/top_level.txt
octopus_cli-0.0.1.dist-info/RECORD
