Metadata-Version: 2.1
Name: octopus-cli
Version: 0.0.1
Summary: Octopus is a devOps toolset
Home-page: https://bitbucket.ascs.tech/projects/TOOL/repos/octopus-cli
Author: Zhao Wei
Author-email: zhaowei@ascs.tech
License: unlicensed
Platform: UNKNOWN
